MANIFEST.in
README.txt
setup.py
pyramid_openid/__init__.py
pyramid_openid/view.py
pyramid_openid.egg-info/PKG-INFO
pyramid_openid.egg-info/SOURCES.txt
pyramid_openid.egg-info/dependency_links.txt
pyramid_openid.egg-info/requires.txt
pyramid_openid.egg-info/top_level.txt