Metadata-Version: 1.0
Name: pyramid-openid
Version: 0.3.4
Summary: A view for pyramid that functions as an OpenID consumer.
Home-page: http://github.com/tomlikestorock/pyramid_openid
Author: Thomas Hill
Author-email: tomlikestorock@gmail.com
License: BSD-derived (http://www.repoze.org/LICENSE.txt)
Keywords: pyramid openid
Platform: UNKNOWN
Classifier: Framework :: Pylons
Classifier: Intended Audience :: Developers
Classifier: License :: Repoze Public License
Classifier: Programming Language :: Python
Classifier: Topic :: Internet :: WWW/HTTP
Classifier: Topic :: Internet :: WWW/HTTP :: WSGI
